jqdatapy/__init__.py
jqdatapy/api.py
jqdatapy/config.json
jqdatapy-0.1.8.dist-info/LICENSE
jqdatapy-0.1.8.dist-info/METADATA
jqdatapy-0.1.8.dist-info/WHEEL
jqdatapy-0.1.8.dist-info/top_level.txt
jqdatapy-0.1.8.dist-info/RECORD
