Metadata-Version: 2.1
Name: jqdatapy
Version: 0.1.8
Summary: unified,modular quantitative system for human beings 
Home-page: https://github.com/zvtvz/jqdatapy
Author: foolcage
Author-email: 5533061@qq.com
Project-URL: Bug Reports, https://github.com/zvtvz/jqdatapy/issues
Project-URL: Funding, https://www.foolcage.com/zvt
Project-URL: Say Thanks!, https://saythanks.io/to/foolcage
Project-URL: Source, https://github.com/zvtvz/jqdatapy
Keywords: quant stock finance fintech big-data zvt technical-analysis trading-platform pandas fundamental-analysis
Classifier: Development Status :: 5 - Production/Stable
Classifier: Intended Audience :: Developers
Classifier: Intended Audience :: Customer Service
Classifier: Intended Audience :: Education
Classifier: Intended Audience :: Financial and Insurance Industry
Classifier: Topic :: Software Development :: Build Tools
Classifier: Topic :: Office/Business :: Financial :: Investment
Classifier: License :: OSI Approved :: MIT License
Classifier: Programming Language :: Python :: 3.6
Classifier: Programming Language :: Python :: 3.7
Classifier: Programming Language :: Python :: 3.8
License-File: LICENSE
Requires-Dist: pandas (>=0.25.3)
